tomp3/__init__.py
tomp3/__main__.py
tomp3/args.py
tomp3/log_config.py
tomp3/path_resolver.py
tomp3/ui/__init__.py
tomp3/ui/custom_types.py
tomp3/ui/file_status.py
tomp3/ui/files_view.py
tomp3/ui/null_ui.py
tomp3/ui/progress_tracker.py
tomp3/ui/ui.py
tomp3/ui/ui_protocol.py
tomp3-1.0.2.dist-info/METADATA
tomp3-1.0.2.dist-info/WHEEL
tomp3-1.0.2.dist-info/entry_points.txt
tomp3-1.0.2.dist-info/licenses/LICENSE
tomp3-1.0.2.dist-info/RECORD
