Metadata-Version: 2.4
Name: tomp3
Version: 1.0.2
Summary: Convert audio files to mp3 format
Project-URL: Homepage, https://github.com/danilo-alm/tomp3
Project-URL: Issues, https://github.com/danilo-alm/tomp3/issues
Author-email: Danilo Almeida <cs.daniloalmeida@gmail.com>
License-Expression: GPL-3.0-only
License-File: LICENSE
Classifier: Operating System :: OS Independent
Classifier: Programming Language :: Python :: 3
Requires-Python: >=3.10
Requires-Dist: rich>=14.0.0
